agent_factory/__init__.py
agent_factory/cli.py
agent_factory/agent/__init__.py
agent_factory/agent/config.py
agent_factory/agent/factory.py
agent_factory/agent/service_factory.py
agent_factory/mcp_server/__init__.py
agent_factory/mcp_server/config.py
agent_factory/mcp_server/manager.py
agent_factory/mcp_server/provider.py
agent_factory/mcp_server/provider_impl.py
openai_agent_factory-0.2.5.dist-info/licenses/LICENSE
openai_agent_factory-0.2.5.dist-info/METADATA
openai_agent_factory-0.2.5.dist-info/WHEEL
openai_agent_factory-0.2.5.dist-info/entry_points.txt
openai_agent_factory-0.2.5.dist-info/top_level.txt
openai_agent_factory-0.2.5.dist-info/RECORD
