Metadata-Version: 2.4
Name: openai-agent-factory
Version: 0.2.5
Summary: SDK for creating and managing OpenAI agents with MCP server integration
Author-email: Jiahao Zhu <jiahzhu@outlook.com>
Project-URL: Repository, https://github.com/jiahzhu1989/agent-factory
Project-URL: Issues, https://github.com/jiahzhu1989/agent-factory/issues
Project-URL: Documentation, https://github.com/jiahzhu1989/agent-factory/tree/main/docs
Keywords: openai,agent,mcp,server,factory,sdk,service,sse,http
Classifier: Development Status :: 4 - Beta
Classifier: Intended Audience :: Developers
Classifier: Programming Language :: Python :: 3.10
Classifier: Programming Language :: Python :: 3.11
Classifier: Topic :: Software Development :: Libraries :: Python Modules
Requires-Python: >=3.10
License-File: LICENSE
Requires-Dist: openai>=1.77.0
Requires-Dist: openai-agents>=0.0.14
Requires-Dist: pydantic>=2.0.0
Requires-Dist: pydantic-settings>=2.0.0
Requires-Dist: python-dotenv>=1.0.0
Requires-Dist: pyyaml>=6.0.0
Requires-Dist: fastapi>=0.110.0
Requires-Dist: uvicorn>=0.27.0
Provides-Extra: dev
Requires-Dist: pytest>=7.0.0; extra == "dev"
Requires-Dist: pytest-asyncio>=0.18.0; extra == "dev"
Requires-Dist: pytest-cov>=3.0.0; extra == "dev"
Requires-Dist: black>=22.0.0; extra == "dev"
Requires-Dist: isort>=5.10.0; extra == "dev"
Requires-Dist: mypy>=0.931; extra == "dev"
Requires-Dist: sphinx>=4.4.0; extra == "dev"
Requires-Dist: sphinx-rtd-theme>=1.0.0; extra == "dev"
Dynamic: license-file
